LICENSE
MANIFEST.in
README.md
setup.py
django_rest_encrypted_lookup.egg-info/PKG-INFO
django_rest_encrypted_lookup.egg-info/SOURCES.txt
django_rest_encrypted_lookup.egg-info/dependency_links.txt
django_rest_encrypted_lookup.egg-info/requires.txt
django_rest_encrypted_lookup.egg-info/top_level.txt
rest_framework_encrypted_lookup/__init__.py
rest_framework_encrypted_lookup/fields.py
rest_framework_encrypted_lookup/serializers.py
rest_framework_encrypted_lookup/settings.py
rest_framework_encrypted_lookup/utils.py
rest_framework_encrypted_lookup/views.py